human_regex/__about__.py
human_regex/__init__.py
human_regex/utilities.py
human_regex/bases/__init__.py
human_regex/bases/general_regex.py
human_regex/bases/re_proxy.py
human_regex/contracts/__init__.py
human_regex/contracts/abstract_regex.py
human_regex-0.1.1.dist-info/METADATA
human_regex-0.1.1.dist-info/WHEEL
human_regex-0.1.1.dist-info/RECORD
