Metadata-Version: 2.3
Name: human-regex
Version: 0.1.1
Summary: Regular expressions for humans
Project-URL: Documentation, https://fleetingbytes.github.io/human-regex/human_regex.html
Project-URL: Issues, https://github.com/fleetingbytes/human-regex/issues
Project-URL: Source, https://github.com/fleetingbytes/human-regex
Author-email: Sven Siegmund <sven.siegmund@gmail.com>
License-Expression: BSD-3-Clause
Classifier: Development Status :: 5 - Production/Stable
Classifier: Programming Language :: Python
Classifier: Programming Language :: Python :: 3.11
Classifier: Programming Language :: Python :: Implementation :: CPython
Classifier: Programming Language :: Python :: Implementation :: PyPy
Requires-Python: >=3.9
